pqcow/__init__.py
pqcow/__version__.py
pqcow/client/__init__.py
pqcow/client/async_client.py
pqcow/client/base.py
pqcow/client/db/__init__.py
pqcow/client/db/base.py
pqcow/client/db/db.py
pqcow/client/db/models/__init__.py
pqcow/client/db/models/chats.py
pqcow/client/db/models/identity.py
pqcow/client/db/models/known_users.py
pqcow/client/db/models/messages.py
pqcow/pq_func/__init__.py
pqcow/pq_func/data.py
pqcow/pq_types/__init__.py
pqcow/pq_types/signed_data.py
pqcow/pq_types/answer_types/__init__.py
pqcow/pq_types/answer_types/answer.py
pqcow/pq_types/answer_types/chat_list_answer.py
pqcow/pq_types/answer_types/error.py
pqcow/pq_types/answer_types/handshake.py
pqcow/pq_types/answer_types/message.py
pqcow/pq_types/answer_types/ok.py
pqcow/pq_types/answer_types/poll_messages_answer.py
pqcow/pq_types/answer_types/resolved_user.py
pqcow/pq_types/request_types/__init__.py
pqcow/pq_types/request_types/chat_list.py
pqcow/pq_types/request_types/poll_messages.py
pqcow/pq_types/request_types/register_request.py
pqcow/pq_types/request_types/resolve_user.py
pqcow/pq_types/request_types/send_handshake.py
pqcow/pq_types/request_types/send_message.py
pqcow/pq_types/request_types/send_request.py
pqcow/server/__init__.py
pqcow/server/client_data.py
pqcow/server/exceptions.py
pqcow/server/server.py
pqcow/server/db/__init__.py
pqcow/server/db/base.py
pqcow/server/db/db.py
pqcow/server/db/models/__init__.py
pqcow/server/db/models/chats.py
pqcow/server/db/models/messages.py
pqcow/server/db/models/users.py
pqcow-0.0.1.dist-info/METADATA
pqcow-0.0.1.dist-info/WHEEL
pqcow-0.0.1.dist-info/licenses/LICENSE
pqcow-0.0.1.dist-info/RECORD
