Metadata-Version: 2.3
Name: pqcow
Version: 0.0.1
License: MIT
Requires-Python: >=3.12
Requires-Dist: aiosqlite==0.20.0
Requires-Dist: cryptography==44.0.0
Requires-Dist: msgspec==0.18.6
Requires-Dist: pqcow-liboqs==0.10.1.dev0
Requires-Dist: sqlalchemy==2.0.36
Requires-Dist: websockets==14.1
Provides-Extra: client
Requires-Dist: textual==0.89.1; extra == 'client'
Provides-Extra: dev
Requires-Dist: isort==5.13.2; extra == 'dev'
Requires-Dist: pre-commit==4.0.1; extra == 'dev'
Requires-Dist: ruff==0.8.2; extra == 'dev'
Requires-Dist: textual-dev==1.7.0; extra == 'dev'
Provides-Extra: lint
Requires-Dist: mypy==1.13.0; extra == 'lint'
Requires-Dist: types-pytz==2024.2.0.20241003; extra == 'lint'
Provides-Extra: uvloop
Requires-Dist: uvloop==0.21.0; (sys_platform == 'linux' or sys_platform == 'darwin') and extra == 'uvloop'
